gcl/__init__.py
gcl/ast.py
gcl/ast_util.py
gcl/doc.py
gcl/exceptions.py
gcl/framework.py
gcl/functions.py
gcl/imp_util.py
gcl/printer.py
gcl/query.py
gcl/runtime.py
gcl/schema.py
gcl/to_json.py
gcl/util.py
gcl-0.6.11.dist-info/DESCRIPTION.rst
gcl-0.6.11.dist-info/METADATA
gcl-0.6.11.dist-info/RECORD
gcl-0.6.11.dist-info/WHEEL
gcl-0.6.11.dist-info/entry_points.txt
gcl-0.6.11.dist-info/metadata.json
gcl-0.6.11.dist-info/top_level.txt
