Metadata-Version: 2.0
Name: gcl
Version: 0.6.11
Summary: Generic Configuration Language
Home-page: https://github.com/rix0rrr/gcl
Author: Rico Huijbers
Author-email: rix0rrr@gmail.com
License: MIT
Keywords: configuration
Platform: UNKNOWN
Classifier: Development Status :: 3 - Alpha
Classifier: Intended Audience :: Developers
Classifier: Topic :: Software Development :: Interpreters
Classifier: License :: OSI Approved :: MIT License
Classifier: Programming Language :: Python :: 2
Classifier: Programming Language :: Python :: 2.6
Classifier: Programming Language :: Python :: 2.7
Classifier: Programming Language :: Python :: 3
Classifier: Programming Language :: Python :: 3.2
Classifier: Programming Language :: Python :: 3.3
Classifier: Programming Language :: Python :: 3.4
Requires-Dist: pyparsing (>=2.0.3)
